odoo/addons/survey_contact_generation/README.rst
odoo/addons/survey_contact_generation/__init__.py
odoo/addons/survey_contact_generation/__manifest__.py
odoo/addons/survey_contact_generation/demo/survey_contact_generation_demo.xml
odoo/addons/survey_contact_generation/i18n/es.po
odoo/addons/survey_contact_generation/i18n/survey_contact_generation.pot
odoo/addons/survey_contact_generation/models/__init__.py
odoo/addons/survey_contact_generation/models/survey_question.py
odoo/addons/survey_contact_generation/models/survey_survey.py
odoo/addons/survey_contact_generation/models/survey_user_input.py
odoo/addons/survey_contact_generation/readme/CONFIGURE.rst
odoo/addons/survey_contact_generation/readme/CONTRIBUTORS.rst
odoo/addons/survey_contact_generation/readme/DESCRIPTION.rst
odoo/addons/survey_contact_generation/readme/USAGE.rst
odoo/addons/survey_contact_generation/static/description/icon.png
odoo/addons/survey_contact_generation/static/description/index.html
odoo/addons/survey_contact_generation/static/tests/survey_contact_generation_tour.js
odoo/addons/survey_contact_generation/tests/__init__.py
odoo/addons/survey_contact_generation/tests/test_survey_contact_generation.py
odoo/addons/survey_contact_generation/views/assets.xml
odoo/addons/survey_contact_generation/views/survey_question_views.xml
odoo/addons/survey_contact_generation/views/survey_survey_views.xml
odoo13_addon_survey_contact_generation-13.0.1.1.0.dist-info/METADATA
odoo13_addon_survey_contact_generation-13.0.1.1.0.dist-info/WHEEL
odoo13_addon_survey_contact_generation-13.0.1.1.0.dist-info/top_level.txt
odoo13_addon_survey_contact_generation-13.0.1.1.0.dist-info/RECORD
